pyttb/__init__.py
pyttb/cp_als.py
pyttb/cp_apr.py
pyttb/create_problem.py
pyttb/export_data.py
pyttb/gcp_opt.py
pyttb/hosvd.py
pyttb/import_data.py
pyttb/khatrirao.py
pyttb/ktensor.py
pyttb/py.typed
pyttb/pyttb_utils.py
pyttb/sptenmat.py
pyttb/sptensor.py
pyttb/sumtensor.py
pyttb/tenmat.py
pyttb/tensor.py
pyttb/ttensor.py
pyttb/tucker_als.py
pyttb/gcp/__init__.py
pyttb/gcp/fg.py
pyttb/gcp/fg_est.py
pyttb/gcp/fg_setup.py
pyttb/gcp/handles.py
pyttb/gcp/optimizers.py
pyttb/gcp/samplers.py
pyttb/matlab/__init__.py
pyttb/matlab/matlab_support.py
pyttb/matlab/matlab_utilities.py
pyttb-1.8.4.dist-info/licenses/LICENSE
pyttb-1.8.4.dist-info/METADATA
pyttb-1.8.4.dist-info/WHEEL
pyttb-1.8.4.dist-info/top_level.txt
pyttb-1.8.4.dist-info/RECORD
