Metadata-Version: 2.4
Name: pyttb
Version: 1.8.4
Summary: Python Tensor Toolbox
Author-email: "Daniel M. Dunlavy" <dmdunla@sandia.gov>
License: BSD 2-Clause License
Project-URL: homepage, https://github.com/sandialabs/pyttb
Project-URL: coverage, https://coveralls.io/github/sandialabs/pyttb
Project-URL: documentation, https://pyttb.readthedocs.io
Classifier: License :: OSI Approved :: BSD License
Classifier: Operating System :: OS Independent
Classifier: Programming Language :: Python :: 3.10
Classifier: Programming Language :: Python :: 3.11
Classifier: Programming Language :: Python :: 3.12
Classifier: Programming Language :: Python :: 3.13
Classifier: Programming Language :: Python :: 3.14
Requires-Python: >=3.10
License-File: LICENSE
Requires-Dist: numpy<2.4,>=1.24
Requires-Dist: numpy_groupies>0.11
Requires-Dist: scipy<1.17,>1.9
Requires-Dist: matplotlib>3.7
Provides-Extra: dev
Requires-Dist: mypy<1.16.0,>=1.15; extra == "dev"
Requires-Dist: nbstripout<0.9,>=0.8; extra == "dev"
Requires-Dist: pytest>8.0; extra == "dev"
Requires-Dist: pytest-cov>5.0; extra == "dev"
Requires-Dist: ruff<0.13,>=0.12; extra == "dev"
Requires-Dist: pre-commit<5.0,>=4.0; extra == "dev"
Requires-Dist: codespell<2.4.0,>=2.3.0; extra == "dev"
Provides-Extra: doc
Requires-Dist: sphinx>=4.0; extra == "doc"
Requires-Dist: sphinx_rtd_theme>2.0; extra == "doc"
Requires-Dist: myst-nb>1.0; extra == "doc"
Provides-Extra: profiling
Requires-Dist: gprof2dot; extra == "profiling"
Requires-Dist: graphviz; extra == "profiling"
Dynamic: license-file
